vec_noise/__init__.py
vec_noise/_perlin.cp36-win32.pyd
vec_noise/_simplex.cp36-win32.pyd
vec_noise/perlin.py
vec_noise/shader.py
vec_noise/shader_noise.py
vec_noise/test.py
vec_noise-1.1.4.dist-info/DESCRIPTION.rst
vec_noise-1.1.4.dist-info/METADATA
vec_noise-1.1.4.dist-info/RECORD
vec_noise-1.1.4.dist-info/WHEEL
vec_noise-1.1.4.dist-info/metadata.json
vec_noise-1.1.4.dist-info/top_level.txt
