Metadata-Version: 2.0
Name: vec-noise
Version: 1.1.4
Summary: Vectorized Perlin noise for Python
Home-page: https://github.com/zbenjamin/vec_noise
Author: Zev Benjamin
Author-email: zev@strangersgate.com
License: UNKNOWN
Platform: UNKNOWN
Classifier: Development Status :: 4 - Beta
Classifier: Topic :: Multimedia :: Graphics
Classifier: License :: OSI Approved :: MIT License
Classifier: Operating System :: MacOS :: MacOS X
Classifier: Operating System :: Microsoft :: Windows
Classifier: Operating System :: POSIX
Classifier: Programming Language :: C
Classifier: Programming Language :: Python :: 2
Classifier: Programming Language :: Python :: 3
Requires-Dist: numpy
